__init__.py
propertyplus.py
PropertyPlus-1.0.10.dist-info/LICENSE.md
PropertyPlus-1.0.10.dist-info/METADATA
PropertyPlus-1.0.10.dist-info/WHEEL
PropertyPlus-1.0.10.dist-info/top_level.txt
PropertyPlus-1.0.10.dist-info/RECORD
