Metadata-Version: 2.1
Name: PropertyPlus
Version: 1.0.10
Summary: A heavily improved subclass of the `property` descriptor, plus more.
Author-email: "J.T. Hartzfeld" <J.T.Hartzfeld@jthdevelops.com>
Project-URL: Homepage, https://github.com/JTHDevelops/propertyplus
Project-URL: Bug Tracker, https://github.com/JTHDevelops/propertyplus/issues
Classifier: Programming Language :: Python :: 3
Classifier: License :: OSI Approved :: MIT License
Classifier: Operating System :: OS Independent
Requires-Python: >=3.11
License-File: LICENSE.md
Requires-Dist: auto_all>=1.4.1
